stalin_sort/__init__.py
stalin_sort/core.py
stalin_sort/py.typed
stalin_sort_python-1.0.1.dist-info/METADATA
stalin_sort_python-1.0.1.dist-info/WHEEL
stalin_sort_python-1.0.1.dist-info/licenses/LICENSE
stalin_sort_python-1.0.1.dist-info/RECORD
