Metadata-Version: 2.4
Name: stalin-sort-python
Version: 1.0.1
Summary: A typed 'Stalin Sort' implementation with strict/decreasing/key options.
Project-URL: Homepage, https://github.com/hofjak/stalin-sort
Project-URL: Issues, https://github.com/hofjak/stalin-sort/issues
Author-email: Jakob Hofer <jakob.refoh@gmail.com>
License: MIT License
License-File: LICENSE
Keywords: algorithms,filter,functional,sorting,typing
Classifier: Development Status :: 5 - Production/Stable
Classifier: License :: OSI Approved :: MIT License
Classifier: Operating System :: OS Independent
Classifier: Programming Language :: Python :: 3
Classifier: Typing :: Typed
Requires-Python: >=3.9
Provides-Extra: dev
Requires-Dist: isort>=6.0.1; extra == 'dev'
Requires-Dist: mypy>=1.18.2; extra == 'dev'
Requires-Dist: pytest>=8.4.2; extra == 'dev'
